{
  "name": "Pappu Singh",
  "applied_role": "housekeeping",
  "language": "hi",
  "answers": {
    "location_and_age": {
      "question": "सबसे पहले, मुझे बताइए कि आप कहाँ रहते हैं — आपका गाँव या शहर — और आपकी उम्र क्या है।",
      "answer": "मैं अयोध्या का निवासी हूँ, यह एक शहर है और मेरी उम्र बत्तीस वर्ष है।"
    },
    "languages": {
      "question": "आप कौन-कौन सी भाषाएँ आराम से बोल सकते हैं?",
      "answer": "मुझे हिंदी भाषा का बहुत अच्छा ज्ञान है और थोड़ा बहुत मैं अंग्रेजी भी जानता हूँ।"
    },
    "family": {
      "question": "अपने परिवार के बारे में थोड़ा बताइए — क्या आप शादीशुदा हैं, और क्या कोई आप पर निर्भर है?",
      "answer": "मेरे परिवार में 7 सदस्य हैं, मेरे माता-पिता, मेरी पत्नी, मेरे 2 पुत्र और मेरे 2 भाई।"
    },
    "education": {
      "question": "आपने अधिकतम किस कक्षा या डिग्री तक पढ़ाई की है, और कहाँ से?",
      "answer": "मैंने बैचलर डिग्री गोरखपुर यूनिवर्सिटी से कंप्लीट किया है।"
    },
    "experience": {
      "question": "क्या आपने पहले कोई काम किया है? अगर हाँ, तो अपनी पिछली नौकरी के बारे में संक्षेप में बताइए — कहाँ काम किया, क्या काम किया, और कितने समय तक।",
      "answer": "मैं गोरखपुर में एक रेस्टोरेंट में सुपरवाइजर था जहां मेरा काम था साफ सफाई करना और साफ सफाई करवाना अपने टीम से और वहां पर मैंने दो वर्ष काम किया"
    },
    "salary": {
      "question": "आप कितनी मासिक तनख्वाह की उम्मीद रखते हैं, और अगर पहले काम किया है तो वहाँ कितनी तनख्वाह मिलती थी?",
      "answer": "मैं बीस हज़ार रुपये मासिक तनख्वाह की उम्मीद रखता हूँ, जहाँ मैंने पहले काम किया था वहाँ मुझे पंद्रह हज़ार मासिक तनख्वाह मिलती थी।"
    },
    "availability": {
      "question": "आप काम कब से शुरू कर सकते हैं, और अगर ज़रूरत पड़े तो क्या आप किसी दूसरे शहर जाने को तैयार हैं?",
      "answer": "मैं कार्य 2 हफ़्ते बाद शुरू कर सकता हूँ और मैं दूसरी जगह जाने के लिए बिल्कुल तैयार हूँ।"
    }
  }
}